fancytools/__init__.py
fancytools/tests.py
fancytools/fcollections/FIFObuffer.py
fancytools/fcollections/MultiList.py
fancytools/fcollections/NestedOrderedDict.py
fancytools/fcollections/ProxyList.py
fancytools/fcollections/TwoDArraySliceIterator.py
fancytools/fcollections/WeakList.py
fancytools/fcollections/__init__.py
fancytools/fcollections/naturalSorting.py
fancytools/fcollections/removeDuplicates.py
fancytools/filter/__init__.py
fancytools/filter/movingAverage.py
fancytools/fit/__init__.py
fancytools/fit/fit2dArrayToFn.py
fancytools/fit/linregressIgnoringOutliers.py
fancytools/fit/polyFitIgnoringOutliers.py
fancytools/geometry/__init__.py
fancytools/geometry/gridLinesFromVertices.py
fancytools/geometry/polylines.py
fancytools/math/MaskedMovingAverage.py
fancytools/math/MovingAverage.py
fancytools/math/Point3D.py
fancytools/math/__init__.py
fancytools/math/angleDiff.py
fancytools/math/blockshaped.py
fancytools/math/boundingBox.py
fancytools/math/execOnSubArrays.py
fancytools/math/findXAt.py
fancytools/math/gridPointsFromEdges.py
fancytools/math/linRegressUsingMasked2dArrays.py
fancytools/math/line.py
fancytools/math/linspace2.py
fancytools/math/nearestPosition.py
fancytools/math/nearestPosition2.py
fancytools/math/pointInsidePolygon.py
fancytools/math/rotatePolygon.py
fancytools/math/rotation.py
fancytools/math/similarity1DdiffShapedArrays.py
fancytools/os/PathStr.py
fancytools/os/StartMenuEntry.py
fancytools/os/__init__.py
fancytools/os/assignFtypeToPyFile.py
fancytools/os/copyTree.py
fancytools/os/countLines.py
fancytools/os/isAdmin.py
fancytools/os/legalizeFilename.py
fancytools/os/runAsAdmin.py
fancytools/os/setup.py
fancytools/os/userName.py
fancytools/pystructure/FallBack.py
fancytools/pystructure/GetCallablesInPackage.py
fancytools/pystructure/__init__.py
fancytools/pystructure/getMembers.py
fancytools/pystructure/runAllInDir.py
fancytools/pystructure/stitchModules.py
fancytools-0.3.1.dist-info/DESCRIPTION.rst
fancytools-0.3.1.dist-info/METADATA
fancytools-0.3.1.dist-info/RECORD
fancytools-0.3.1.dist-info/WHEEL
fancytools-0.3.1.dist-info/metadata.json
fancytools-0.3.1.dist-info/top_level.txt
