Metadata-Version: 2.0
Name: fancytools
Version: 0.3.1
Summary: 
Requires-Dist: numpy (>=1.9)
